anomaly_agent/__init__.py
anomaly_agent/agent.py
anomaly_agent/constants.py
anomaly_agent/plot.py
anomaly_agent/prompt.py
anomaly_agent/utils.py
anomaly_agent-0.13.0.dist-info/METADATA
anomaly_agent-0.13.0.dist-info/WHEEL
anomaly_agent-0.13.0.dist-info/licenses/LICENSE
anomaly_agent-0.13.0.dist-info/RECORD
