Metadata-Version: 2.4
Name: anomaly-agent
Version: 0.13.0
Summary: A package for detecting anomalies in time series data using LLMs
Project-URL: Homepage, https://github.com/andrewm4894/anomaly-agent
Project-URL: Repository, https://github.com/andrewm4894/anomaly-agent
Project-URL: Issues, https://github.com/andrewm4894/anomaly-agent/issues
Author-email: Andrew Maguire <andrewm4894@gmail.com>
License: MIT License
License-File: LICENSE
Keywords: anomaly-detection,llm,machine-learning,time-series
Classifier: Development Status :: 3 - Alpha
Classifier: Intended Audience :: Science/Research
Classifier: License :: OSI Approved :: MIT License
Classifier: Operating System :: OS Independent
Classifier: Programming Language :: Python :: 3
Classifier: Programming Language :: Python :: 3.10
Classifier: Programming Language :: Python :: 3.11
Requires-Python: >=3.10
Requires-Dist: langchain-core
Requires-Dist: langchain-openai
Requires-Dist: langchain>=1.0.3
Requires-Dist: langgraph
Requires-Dist: matplotlib
Requires-Dist: pandas
Requires-Dist: plotly
Requires-Dist: posthog>=6.7.13
Requires-Dist: pydantic
Requires-Dist: python-dotenv
Provides-Extra: dev
Requires-Dist: black; extra == 'dev'
Requires-Dist: flake8; extra == 'dev'
Requires-Dist: isort; extra == 'dev'
Requires-Dist: mypy; extra == 'dev'
Requires-Dist: nbformat; extra == 'dev'
Requires-Dist: pip-tools; extra == 'dev'
Requires-Dist: pre-commit; extra == 'dev'
Requires-Dist: pytest; extra == 'dev'
Requires-Dist: pytest-cov; extra == 'dev'
Requires-Dist: pytest-mock; extra == 'dev'
Requires-Dist: twine; extra == 'dev'
